statsassume/__init__.py
statsassume/datasets.py
statsassume/enums.py
statsassume/explainers.py
statsassume/logger.py
statsassume/plots.py
statsassume/reports.py
statsassume/stats.py
statsassume/tasks.py
statsassume/utils.py
statsassume/layouts/__init__.py
statsassume/layouts/linear_regression/__init__.py
statsassume/layouts/linear_regression/layout.py
statsassume/layouts/linear_regression/tabs.py
statsassume/layouts/logistic_regression/__init__.py
statsassume/layouts/placeholder/__init__.py
statsassume/layouts/placeholder/layout.py
statsassume/layouts/placeholder/tabs.py
statsassume-0.0.5.dist-info/LICENSE
statsassume-0.0.5.dist-info/METADATA
statsassume-0.0.5.dist-info/WHEEL
statsassume-0.0.5.dist-info/top_level.txt
statsassume-0.0.5.dist-info/RECORD
