Metadata-Version: 2.1
Name: statsassume
Version: 0.0.5
Summary: Automating Assumption Checks for Regression Models
Home-page: https://github.com/kennethleungty/statsassume
Author: Kenneth Leung
Author-email: statsassume@gmail.com
License: UNKNOWN
Platform: UNKNOWN
Classifier: Programming Language :: Python :: 3
Classifier: License :: OSI Approved :: MIT License
Classifier: Operating System :: OS Independent
Requires-Python: >=3.7
License-File: LICENSE
Requires-Dist: matplotlib (>=3.5.0)
Requires-Dist: numpy (>=1.21.4)
Requires-Dist: pandas (>=1.3.4)
Requires-Dist: scikit-learn (>=1.0.1)
Requires-Dist: scipy (>=1.7.3)
Requires-Dist: seaborn (>=0.11.2)
Requires-Dist: statsmodels (>=0.13.1)
Requires-Dist: lxml (==4.7.1)
Requires-Dist: jupyter-dash (==0.4.1)
Requires-Dist: dash-bootstrap-components (==1.0.2)
